{"name":"henrique andrade","tagline":"econometria e ciência de dados","body":"## Sobre a página\r\n\r\nNessa página tento reunir e compartilhar alguns códigos que desenvolvi para solucionar questões relacionadas a análises econométricas e estatísticas. Em alguns deles utilizei técnicas da ciência de dados (como [data wrangling](https://en.wikipedia.org/wiki/Data_wrangling) e [webscrapping](https://en.wikipedia.org/wiki/Web_scraping)) para obtenção e estruturação das informações dados para análise posterior.\r\n\r\nOs códigos estão escritos em basicamente três linguagens:\r\n\r\n- Hansl (linguagem utilizada pelo pacote econométrico Gretl)\r\n- R\r\n- Python\r\n\r\n## Sobre mim\r\n\r\nSou economista formado pela Universidade Federal de Pernambuco, com mestrado e doutorado, também em economia, pela Universidade Federal da Paraíba e pela Universidade Federal do Rio Grande do Sul, respectivamente.\r\n\r\nFui pesquisador e economista na Diretoria de Estratégia e Organização do Banco do Brasil. Atualmente sou analista na Coordenação-Geral de Modelagem Econômica da Secretaria de Política Econômica do Ministério da Fazenda e faço parte da equipe de desenvolvimento do pacote econométrico Gretl.\r\n\r\nTenho experiência na área de macroeconomia, com ênfase na formulação de cenários e análise de conjuntura, e de econometria aplicada, com ênfase em séries temporais e softwares estatísticos e econométricos.","google":"","note":"Don't delete this file! It's used internally to help with page regeneration."}